MANIFEST.in
NEWS.rst
README.rst
setup.cfg
setup.py
build_scripts/__init__.py
build_scripts/version.py
src/xmlpylighter/RELEASE-VERSION
src/xmlpylighter/__init__.py
src/xmlpylighter/xmlpylighter.py
src/xmlpylighter.egg-info/PKG-INFO
src/xmlpylighter.egg-info/SOURCES.txt
src/xmlpylighter.egg-info/dependency_links.txt
src/xmlpylighter.egg-info/entry_points.txt
src/xmlpylighter.egg-info/not-zip-safe
src/xmlpylighter.egg-info/requires.txt
src/xmlpylighter.egg-info/top_level.txt