Metadata-Version: 1.1
Name: xmlpylighter
Version: v0.1.1
Summary: xmlpylighter is a tiny web page to pretty print and compare xml files 
Home-page: https://github.com/ThomasChiroux/xmlpylighter
Author: Thomas Chiroux
Author-email: UNKNOWN
License: LGPLv3
Keywords: xml diff pprint pretty print
Platform: UNKNOWN
Classifier: Programming Language :: Python
Classifier: Programming Language :: Python :: 2.6
Classifier: Programming Language :: Python :: 2.7
Provides: xmlpylighter
